{
  "id": "highlights",
  "name": "高光混剪",
  "description": "自动挑出评分最高的4-6个片段，快节奏拼接，展示精彩瞬间",
  "tag": "经典款",
  "segmentSelection": {
    "strategy": "top-scored",
    "maxSegments": 6,
    "minDuration": 2,
    "maxDuration": 8,
    "sortBy": "time"
  },
  "layout": {
    "intro": {
      "duration": 0.8,
      "type": "text",
      "text": "🔥 精彩集锦",
      "style": {
        "backgroundColor": "#000000",
        "textColor": "#FFFFFF",
        "fontSize": 72
      }
    }
  },
  "transitions": {
    "type": "slide",
    "duration": 0.22
  },
  "visualStyle": {
    "filter": "vibrant",
    "brightness": 0.06,
    "contrast": 0.12,
    "saturation": 0.16
  },
  "backgroundMusic": {
    "enabled": true,
    "file": "upbeat.mp3",
    "jamendoTags": ["electronic", "dance", "upbeat"],
    "jamendoVocal": "instrumental",
    "volume": 0.24,
    "fadeIn": 0.6,
    "fadeOut": 1.4
  },
  "audioProcessing": {
    "keepOriginal": true,
    "originalVolume": 0.76,
    "normalize": true
  }
}
